cridlib/__init__.py
cridlib/const.py
cridlib/get.py
cridlib/lib.py
cridlib/parse.py
cridlib/strategy/future.py
cridlib/strategy/now.py
cridlib/strategy/past.py
cridlib-0.1.5.dist-info/LICENSE
cridlib-0.1.5.dist-info/WHEEL
cridlib-0.1.5.dist-info/METADATA
cridlib-0.1.5.dist-info/RECORD
