Metadata-Version: 2.1
Name: cridlib
Version: 0.1.5
Summary: Generate CRIDs for RaBe
License: AGPL-3
Author: Lucas Bickel
Author-email: hairmare@rabe.ch
Requires-Python: >=3.9,<4.0
Classifier: License :: Other/Proprietary License
Classifier: Programming Language :: Python :: 3
Classifier: Programming Language :: Python :: 3.9
Classifier: Programming Language :: Python :: 3.10
Classifier: Programming Language :: Python :: 3.11
Requires-Dist: pytz (>=2022.6)
Requires-Dist: requests (>=2.28.1,<3.0.0)
Requires-Dist: uritools (>=4.0.0,<5.0.0)
